{
  "version": 134,
  "time":
  {
    "meter":
    [
      {
        "index": 0,
        "numerator": 4,
        "denominator": 4
      }
    ],
    "tempo":
    [

    ]
  },
  "library":
  [],
  "tracks":
  [
    {
      "name": "未命名音轨",
      "dispColor": "ff7db235",
      "dispOrder": -1,
      "renderEnabled": false,
      "mixer":
      {
        "gainDecibel": 0.0,
        "pan": 0.0,
        "mute": false,
        "solo": false,
        "display": true
      },
      "mainGroup":
      {
        "name": "main",
        "uuid": "298b2eaf-1a42-4cd7-8edb-3dcacafe7a14",
        "parameters":
        {
          "pitchDelta":
          {
            "mode": "cubic",
            "points":
            []
          },
          "vibratoEnv":
          {
            "mode": "cubic",
            "points":
            []
          },
          "loudness":
          {
            "mode": "cubic",
            "points":
            []
          },
          "tension":
          {
            "mode": "cubic",
            "points":
            []
          },
          "breathiness":
          {
            "mode": "cubic",
            "points":
            []
          },
          "voicing":
          {
            "mode": "cubic",
            "points":
            []
          },
          "gender":
          {
            "mode": "cubic",
            "points":
            []
          },
          "toneShift":
          {
            "mode": "cubic",
            "points":
            []
          }
        },
        "vocalModes":
        {},
        "notes":
        [

        ]
      },
      "mainRef":
      {
        "groupID": "298b2eaf-1a42-4cd7-8edb-3dcacafe7a14",
        "blickOffset": 0,
        "pitchOffset": 0,
        "isInstrumental": false,
        "systemPitchDelta":
        {
          "mode": "cubic",
          "points":
          [
            254015987,
            0.0,
            303407986,
            -129.4478149414062,
            324575985,
            -179.6415100097656,
            338687985,
            -200.6356048583984,
            359855984,
            -214.1544647216797,
            366911984,
            -205.9602203369141,
            373967984,
            -167.4184112548828,
            381023984,
            -91.24867248535156,
            388079984,
            -23.13461112976074,
            395135984,
            -11.1572265625,
            402191983,
            -23.13385009765625,
            409247983,
            -26.17263793945312,
            458639982,
            -34.71298217773438,
            479807982,
            -25.20217895507812,
            508031981,
            -28.06320190429688,
            585647979,
            -11.37313842773438,
            656207978,
            -16.25900268554688,
            670319977,
            -12.47177124023438,
            684431977,
            -20.92666625976562,
            698543977,
            -15.51055908203125,
            719711976,
            -20.61767578125,
            769103975,
            -15.02456665039062,
            846719973,
            14.39056396484375,
            860831973,
            11.57150268554688,
            896111972,
            18.61801147460938,
            910223972,
            13.64212036132812,
            945503971,
            15.84320068359375,
            980783970,
            7.256317138671875,
            1016063970,
            10.20584106445312,
            1030175969,
            4.261016845703125,
            1058399969,
            9.368896484375,
            1072511968,
            1.751708984375,
            1107791968,
            -1.947784423828125,
            1121903967,
            5.8013916015625,
            1143071967,
            5.625152587890625,
            1157183967,
            22.48916625976562,
            1164239966,
            25.08773803710938,
            1185407966,
            12.44964599609375,
            1213631965,
            10.247802734375,
            1234799965,
            -0.673675537109375,
            1270079964,
            -30.92498779296875,
            1277135987,
            -31.6494140625,
            1284191987,
            -50.74776840209961,
            1291247986,
            -74.40476989746094,
            1319471986,
            -225.8243713378906,
            1333583985,
            -310.29248046875,
            1340639985,
            -344.2246398925781,
            1347695985,
            -372.0712280273438,
            1361807985,
            -408.2923889160156,
            1368863985,
            -416.0338439941406,
            1375919985,
            -416.7413635253906,
            1382975984,
            -407.4862365722656,
            1390031984,
            -385.8113403320312,
            1397087984,
            -349.5746765136719,
            1411199984,
            -244.0055847167969,
            1418255984,
            -204.9484252929688,
            1425311983,
            -181.5658569335938,
            1432367983,
            -166.2429809570312,
            1453535983,
            -132.9971313476562,
            1460591983,
            -129.1221618652344,
            1474703982,
            -135.1104736328125,
            1509983982,
            -161.5737915039062,
            1524095981,
            -178.6140441894531,
            1538207981,
            -178.5247802734375,
            1552319981,
            -171.9642639160156,
            1559375980,
            -163.2896423339844,
            1587599980,
            -99.22027587890625,
            1608767979,
            -45.8526611328125,
            1629935979,
            -14.23568725585938,
            1636991979,
            -8.77532958984375,
            1742831976,
            6.90155029296875,
            1785167975,
            1.96990966796875,
            1855727974,
            15.93017578125,
            1912175973,
            -7.71484375,
            1947455972,
            -14.9810791015625,
            2025071970,
            -1.2420654296875,
            2039183970,
            -5.117034912109375,
            2102687968,
            -1.153564453125,
            2159135967,
            -17.84210205078125,
            2187359966,
            -18.45855712890625,
            2208527966,
            -5.90972900390625,
            2229695965,
            -4.808807373046875,
            2236751965,
            -0.18463134765625,
            2328479963,
            17.779541015625,
            2342591963,
            9.50164794921875,
            2363759962,
            22.53494262695312,
            2391983962,
            27.37884521484375,
            2420207961,
            21.34552001953125,
            2483711960,
            -1.9927978515625,
            2554271958,
            -10.81466674804688,
            2582495958,
            -6.70013427734375,
            2631887956,
            -9.131622314453125,
            2660111956,
            -1.81732177734375,
            2702447955,
            1.096343994140625,
            2737727954,
            12.64419555664062,
            2744783954,
            10.07308959960938,
            2751839954,
            -10.162353515625,
            2773007953,
            -115.13671875,
            2780063953,
            -125.3242492675781,
            2787119953,
            -90.50216674804688,
            2801231953,
            40.4327392578125,
            2808287953,
            90.19012451171875,
            2815343952,
            134.6145629882812,
            2822399952,
            156.8283081054688,
            2829455952,
            135.3164672851562,
            2836511952,
            102.7717590332031,
            2843567952,
            85.11428833007812,
            2871791951,
            49.75738525390625,
            2892959951,
            33.9508056640625,
            2914127950,
            30.09185791015625,
            2928239950,
            19.96994018554688,
            2956463949,
            9.059906005859375,
            2984687949,
            7.68890380859375,
            3005855948,
            -0.21209716796875,
            3019967948,
            4.253387451171875,
            3034079947,
            2.687835693359375,
            3097583946,
            -10.79177856445312,
            3104639946,
            -6.389617919921875,
            3118751946,
            -14.8529052734375,
            3132863945,
            -11.505126953125,
            3154031945,
            -17.31796264648438,
            3203423944,
            -10.75592041015625,
            3281039942,
            18.61572265625,
            3295151942,
            15.31219482421875,
            3330431941,
            20.7733154296875,
            3344543941,
            15.88668823242188,
            3379823940,
            17.2515869140625,
            3408047939,
            9.10491943359375,
            3450383938,
            11.17477416992188,
            3464495938,
            6.154632568359375,
            3492719937,
            11.83547973632812,
            3506831937,
            5.582427978515625,
            3542111936,
            5.84716796875,
            3556223936,
            14.25704956054688,
            3577391935,
            14.74151611328125,
            3591503935,
            30.8135986328125,
            3598559935,
            33.32366943359375,
            3619727934,
            20.3338623046875,
            3647951934,
            11.17477416992188,
            3669119933,
            -8.24432373046875,
            3690287933,
            -34.04769897460938,
            3704399932,
            -39.5965576171875,
            3725567932,
            -23.43597412109375,
            3782015931,
            72.68753051757812,
            3796127930,
            90.25726318359375,
            3803183930,
            93.16329956054688,
            3824351930,
            87.17498779296875,
            3852575929,
            28.03726196289062,
            3873743929,
            -28.19366455078125,
            3894911928,
            -66.28265380859375,
            3909023928,
            -56.81533813476562,
            3923135928,
            -31.58493041992188,
            3951359927,
            35.43319702148438,
            3965471927,
            61.85302734375,
            3979583926,
            85.455322265625,
            3986639926,
            87.48016357421875,
            4007807926,
            64.67056274414062,
            4050143925,
            -28.9886474609375,
            4064255924,
            -53.20816040039062,
            4071311924,
            -59.24072265625,
            4092479924,
            -56.33468627929688,
            4113647923,
            -42.11196899414062,
            4134815923,
            -16.70608520507812,
            4155983922,
            -10.27679443359375,
            4177151922,
            -20.18508911132812,
            4184207922,
            -32.60269165039062,
            4205375921,
            -96.84677124023438,
            4212431921,
            -98.43292236328125,
            4233599921,
            -48.23532104492188,
            4247711920,
            -33.59830093383789,
            4268879920,
            -2.888999462127686,
            4297103919,
            3.040773868560791,
            4325327919,
            0.9842943549156189,
            4339439918,
            0.0
          ]
        },
        "database":
        {
          "name": "Kasane Teto",
          "language": "japanese",
          "phoneset": "romaji",
          "languageOverride": "",
          "phonesetOverride": "",
          "backendType": "SVR2AI",
          "version": "101"
        },
        "dictionary": "",
        "voice":
        {
          "vocalModeInherited": true,
          "vocalModePreset": "",
          "vocalModeParams":
          {}
        },
        "pitchTakes":
        {
          "activeTakeId": 0,
          "takes":
          [
            {
              "id": 0,
              "expr": 1.0,
              "liked": false
            }
          ]
        },
        "timbreTakes":
        {
          "activeTakeId": 0,
          "takes":
          [
            {
              "id": 0,
              "expr": 1.0,
              "liked": false
            }
          ]
        }
      },
      "groups":
      []
    }
  ],
  "renderConfig":
  {
    "destination": "./",
    "filename": "未命名",
    "numChannels": 1,
    "aspirationFormat": "noAspiration",
    "bitDepth": 16,
    "sampleRate": 44100,
    "exportMixDown": true,
    "exportPitch": false
  }
}